Metadata-Version: 2.1
Name: ohmytable
Version: 0.1.0
Author: Sanster
Maintainer: Sanster
Project-URL: Bug Reports, https://github.com/Sanster/ohmytable/issues
Project-URL: Source, https://github.com/Sanster/ohmytable/
Keywords: deep-learning,table-structure-recognition
Classifier: Intended Audience :: Developers
Classifier: Intended Audience :: Science/Research
Classifier: Programming Language :: Python :: 3
Classifier: Programming Language :: Python :: 3.8
Classifier: Programming Language :: Python :: 3.9
Classifier: Programming Language :: Python :: 3.10
Classifier: Programming Language :: Python :: 3.11
Classifier: Programming Language :: Python :: 3.12
Classifier: Topic :: Software Development
Classifier: Topic :: Scientific/Engineering
Classifier: Topic :: Scientific/Engineering :: Artificial Intelligence
Classifier: Topic :: Scientific/Engineering :: Image Recognition
Classifier: Operating System :: POSIX :: Linux
Classifier: Operating System :: MacOS
Classifier: Operating System :: Microsoft :: Windows
Requires-Python: >=3.8
Requires-Dist: numpy <2.0.0,>=1.23.0
Requires-Dist: opencv-python >=4.6.0
Requires-Dist: torch >=1.8.0
Requires-Dist: torchvision >=0.9.0
Requires-Dist: ultralytics
Requires-Dist: loguru
Requires-Dist: huggingface-hub
Requires-Dist: tokenizers
Requires-Dist: shapely
Requires-Dist: pyclipper
